mycalc/calculator.py
oss01-0.0.1.dist-info/METADATA
oss01-0.0.1.dist-info/WHEEL
oss01-0.0.1.dist-info/top_level.txt
oss01-0.0.1.dist-info/RECORD
