Metadata-Version: 2.1
Name: oss01
Version: 0.0.1
Summary: calculator
Home-page: https://github.com/sejin-chun/calc0001
Download-URL: https://github.com/sejin-chun/calc0001/
Author: jeong won
License: UNKNOWN
Platform: UNKNOWN
Classifier: Programming Language :: Python :: 3 
